pybotchi_cli/__init__.py
pybotchi_cli-0.1.0.dist-info/METADATA
pybotchi_cli-0.1.0.dist-info/WHEEL
pybotchi_cli-0.1.0.dist-info/RECORD
