Metadata-Version: 2.1
Name: pybotchi-cli
Version: 0.1.0
Summary: PyBotchi implementation for executing cli commands
Home-page: https://github.com/amadolid/pybotchi
Author: Alexie (Boyong) Madolid
Author-email: madolid.alexie@gmail.com
Requires-Python: >=3.13.0,<4.0
Classifier: Programming Language :: Python :: 3
Classifier: Programming Language :: Python :: 3.13
Requires-Dist: pybotchi (>=1.0.7)
Project-URL: Repository, https://github.com/amadolid/pybotchi
